[{"s": "keli-xk3118-podklyuchenie-com-port", "t": "Подключение Keli XK3118 через COM-порт: Инструкция", "i": "📁", "c": null}, {"s": "keenetic-hero-4g-problema-s-modemom", "t": "Keenetic Hero 4G+: решение проблем с USB-модемом", "i": "🌐", "c": "internet-routery"}, {"s": "keenetic-ne-v-seti-megafon", "t": "Keenetic не в сети МегаФон: решение проблем 4G/LTE", "i": "🌐", "c": "internet-routery"}, {"s": "keenetic-dlya-pk", "t": "Настройка Keenetic для ПК: полное руководство по подключению", "i": "🌐", "c": "internet-routery"}, {"s": "kerui-kamera-videonablyudeniya-wifi-prilozhenie-c45", "t": "Kerui C45: настройка Wi-Fi камеры и приложение", "i": "📱", "c": "android-smartfony"}, {"s": "kerlii-kamera-videonablyudeniya-skachat-prilozhenie", "t": "Kerlii камера: как скачать и установить приложение для видеонаблюдения", "i": "📱", "c": "android-smartfony"}, {"s": "keenetic-hero-4g-otvalilsya-modem", "t": "Keenetic Hero 4G+ не видит модем: решение проблемы", "i": "📺", "c": "nastroika-tv"}, {"s": "keenetic-hero-prosedaet-internet", "t": "Keenetic Hero: причины низкой скорости и просадок интернета", "i": "🌐", "c": "internet-routery"}, {"s": "kerui-prilozhenie-na-videokamera", "t": "Настройка Kerui для видеокамер: полная инструкция", "i": "📱", "c": "android-smartfony"}, {"s": "keenetic-dlya-chego-internet-filtry", "t": "Keenetic: зачем нужны интернет-фильтры и как их настроить", "i": "🌐", "c": "internet-routery"}, {"s": "kerui-program-kamera", "t": "Kerui Program Camera: Настройка и управление камерами", "i": "📷", "c": "foto-kamery"}, {"s": "keyplan-3d-na-kompyuter-na-russkom", "t": "Keyplan 3D на ПК: установка и работа через эмулятор", "i": "🌐", "c": "internet-routery"}, {"s": "keenetic-skachat-prilozhenie-na-pk", "t": "Keenetic скачать приложение на ПК: установка и настройка", "i": "📱", "c": "android-smartfony"}, {"s": "keenetic-hero-mozhem-ne-gotov", "t": "Keenetic Hero не готов: причины и решение проблемы", "i": "🌐", "c": "internet-routery"}, {"s": "keenetic-4g-hero-perestal-lovit-set", "t": "Keenetic 4G Hero+ не ловит сеть: причины и решения", "i": "🌐", "c": "internet-routery"}, {"s": "keenetic-hero-4g-zavisaet", "t": "Keenetic Hero 4G+ зависает: причины и способы устранения", "i": "🌐", "c": "internet-routery"}, {"s": "keenetic-hero-posle-obnovleniya-sletel-router", "t": "Keenetic Hero слетел после обновления: восстановление и настройка", "i": "🌐", "c": "internet-routery"}, {"s": "kernel-launcher", "t": "Kernel Launcher: Установка и настройка ядра на Android", "i": "📁", "c": null}, {"s": "keli-xk3118t1-com-port", "t": "Keli XK3118T1 COM-порт: Настройка и подключение к ПК", "i": "📁", "c": null}, {"s": "kerui-k268-kak-vklyuchit-zapis", "t": "Запись на Kerui K268: инструкция по настройке DVR и SD-карты", "i": "📲", "c": "prilozheniya-servisy"}, {"s": "keenetic-hero-4g-teryaet-svyaz", "t": "Keenetic Hero 4G теряет связь: причины и устранение", "i": "🌐", "c": "internet-routery"}, {"s": "keenetic-hero-4g-ustanovka-prilozhenij", "t": "Keenetic Hero 4G+: Установка приложений и расширений", "i": "🌐", "c": "internet-routery"}, {"s": "kernel-pnp-411-usb", "t": "Ошибка Kernel PnP 411: Решение проблем с USB-устройствами", "i": "💻", "c": "windows-pk"}, {"s": "kerui-kamera-domashnyaya-rukovodstvo", "t": "Kerui Камера Домашняя Руководство: Настройка, Сброс и Ошибки", "i": "📺", "c": "nastroika-tv"}, {"s": "keenetic-giga-rezhim-usilitel", "t": "Keenetic Giga в режиме усилителя: настройка и оптимизация", "i": "🌐", "c": "internet-routery"}, {"s": "keenetic-hero-4g-kn-2311-postoyanno-teryaet-internet", "t": "Keenetic Hero 4G теряет интернет: полный разбор причин", "i": "🌐", "c": "internet-routery"}, {"s": "keenetic-1012-teryaetsya-internet", "t": "Keenetic 1012: пропал интернет – причины и методы устранения", "i": "🌐", "c": "internet-routery"}, {"s": "keenetic-kn1713-i-modem-3372s-otvalivaetsya-internet", "t": "Keenetic KN-1713 и модем 3372s: устранение обрывов интернета", "i": "📺", "c": "nastroika-tv"}, {"s": "keenetic-hero-4g-problema-s-dns", "t": "Keenetic Hero 4G+: решение проблем с DNS", "i": "🌐", "c": "internet-routery"}, {"s": "keenetic-hero-4g-kn-2310-otvalivaetsya-mobilnyj-internet-bilajn", "t": "Keenetic Hero 4G (KN-2310) и Билайн: устранение обрывов", "i": "📺", "c": "nastroika-tv"}, {"s": "kerui-kamera-videonablyudeniya-wifi-prilozhenie", "t": "Камера Kerui WiFi: настройка приложения и устранение ошибок", "i": "📱", "c": "android-smartfony"}, {"s": "kerui-pzt-kamera-nastrojka-nachalnoj-tochki-otslezhivaniya-dvizheniya", "t": "Настройка начальной точки отслеживания камеры Kerui PZT", "i": "📷", "c": "foto-kamery"}, {"s": "keweisi-kws-dc-200-svyaz-po-blyutuz", "t": "Keweisi KWS DC 200: настройка Bluetooth и работа", "i": "📁", "c": null}, {"s": "keenetic-hero-4g-ne-gorit-signal-set-chto-delat", "t": "Keenetic Hero 4G+ нет индикатора сети: причины и решение", "i": "🌐", "c": "internet-routery"}, {"s": "keenetic-hero-4g-teryaet-svyaz-lte", "t": "Keenetic Hero 4G+ теряет LTE: причины и решение", "i": "🌐", "c": "internet-routery"}, {"s": "keenetic-runner-4g-n300-gorit-sinim-vajfaj-s-vyshkoj-chto-zeachit-ne-gruzit", "t": "Keenetic Runner 4G: синий индикатор Wi-Fi, есть сеть, но нет интернета", "i": "🌐", "c": "internet-routery"}, {"s": "keenetic-2669-plokho-lovit-internet", "t": "Keenetic 2669: устранение проблем с Wi-Fi и интернетом", "i": "🌐", "c": "internet-routery"}, {"s": "keenetic-4g-1212-postoyanno-otvalivaetsya-internet-chto-delat", "t": "Keenetic 4G (KN-1212) теряет сеть: причины и решение", "i": "📺", "c": "nastroika-tv"}, {"s": "keenetic-hero-4g-problemy", "t": "Keenetic Hero 4G+: решение проблем со скоростью и стабильностью", "i": "🌐", "c": "internet-routery"}]